{
  "ToDoNotes": [
    {
      "Title": "Todo Note Test",
      "Items": [
        "Note 1",
        "Note 2"
      ],
      "Id": 2,
      "Timestamp": "2021-05-25T01:05:30.76213+01:00"
    },
    {
      "Title": "GetById Test1",
      "Items": [
        "Note 1 Test 1",
        "Note 2 Test 1"
      ],
      "Id": 5,
      "Timestamp": "2021-05-25T01:05:30.9211092+01:00"
    },
    {
      "Title": "GetById Test2",
      "Items": [
        "Note 1 Test 2",
        "Note 2 Test 2"
      ],
      "Id": 6,
      "Timestamp": "2021-05-25T01:05:30.9269936+01:00"
    },
    {
      "Title": "Todo Note Postman test",
      "Items": [
        "Postman 1",
        "Postman 2"
      ],
      "Id": 8,
      "Timestamp": "2021-05-25T01:12:57.3412231+01:00"
    },
    {
      "Title": "Todo Note Postman test",
      "Items": [
        "Postman 1",
        "Postman 2"
      ],
      "Id": 9,
      "Timestamp": "2021-05-25T01:15:13.310576+01:00"
    },
    {
      "Title": "Todo Note Postman test",
      "Items": [
        "Postman 1",
        "Postman 2"
      ],
      "Id": 10,
      "Timestamp": "2021-05-25T01:37:18.3578705+01:00"
    },
    {
      "Title": "Update Postman test",
      "Items": [
        "Update Postman 1",
        "Update Postman 2",
        "Update Postman 3"
      ],
      "Id": 1,
      "Timestamp": "2021-05-25T01:41:01.9283457+01:00"
    },
    {
      "Title": "Todo Note Test",
      "Items": [
        "Note 1",
        "Note 2"
      ],
      "Id": 11,
      "Timestamp": "2021-05-25T01:45:23.2738551+01:00"
    },
    {
      "Title": "Update TestUpdated 1",
      "Items": [
        "Note 1",
        "Note 2",
        "Note 3"
      ],
      "Id": 12,
      "Timestamp": "2021-05-25T01:45:23.3762835+01:00"
    },
    {
      "Title": "GetById Test1",
      "Items": [
        "Note 1 Test 1",
        "Note 2 Test 1"
      ],
      "Id": 14,
      "Timestamp": "2021-05-25T01:45:23.4330687+01:00"
    },
    {
      "Title": "GetById Test2",
      "Items": [
        "Note 1 Test 2",
        "Note 2 Test 2"
      ],
      "Id": 15,
      "Timestamp": "2021-05-25T01:45:23.4406261+01:00"
    }
  ],
  "ActualId": 15
}