{
  "AllToDo": [
    {
      "Title": "Todo Note Test",
      "Items": [
        "Note 1",
        "Note 2"
      ],
      "Id": 2,
      "TimeStamp": "2021-05-24T14:00:50.1255509+01:00"
    },
    {
      "Title": "GetById Test1",
      "Items": [
        "Note 1 Test 1",
        "Note 2 Test 1"
      ],
      "Id": 3,
      "TimeStamp": "2021-05-24T18:59:11.8163171+01:00"
    },
    {
      "Title": "GetById Test2",
      "Items": [
        "Note 1 Test 2",
        "Note 2 Test 2"
      ],
      "Id": 4,
      "TimeStamp": "2021-05-24T18:59:14.980574+01:00"
    },
    {
      "Title": "Update Test",
      "Items": [
        "Note 1",
        "Note 2"
      ],
      "Id": 5,
      "TimeStamp": "2021-05-24T20:11:19.0391452+01:00"
    },
    {
      "Title": "Update TestUpdated 1",
      "Items": [
        "Note 1",
        "Note 2",
        "Note 3"
      ],
      "Id": 6,
      "TimeStamp": "2021-05-24T20:11:31.7643115+01:00"
    },
    {
      "Title": "Update Test",
      "Items": [
        "Note 1",
        "Note 2"
      ],
      "Id": 7,
      "TimeStamp": "2021-05-24T20:19:39.1941147+01:00"
    },
    {
      "Title": "Update TestUpdated 1",
      "Items": [
        "Note 1",
        "Note 2",
        "Note 3"
      ],
      "Id": 8,
      "TimeStamp": "2021-05-24T20:19:42.1364973+01:00"
    },
    {
      "Title": "Update TestUpdated 1",
      "Items": [
        "Note 1",
        "Note 2",
        "Note 3"
      ],
      "Id": 9,
      "TimeStamp": "0001-01-01T00:00:00"
    },
    {
      "Title": "Update TestUpdated 1",
      "Items": [
        "Note 1",
        "Note 2",
        "Note 3"
      ],
      "Id": 10,
      "TimeStamp": "0001-01-01T00:00:00"
    },
    {
      "Title": "Update TestUpdated 1",
      "Items": [
        "Note 1",
        "Note 2",
        "Note 3"
      ],
      "Id": 11,
      "TimeStamp": "0001-01-01T00:00:00"
    },
    {
      "Title": "Delete Test",
      "Items": [
        "Note 1",
        "Note 2"
      ],
      "Id": 12,
      "TimeStamp": "2021-05-24T20:34:33.4283265+01:00"
    },
    {
      "Title": "Delete Test",
      "Items": [
        "Note 1",
        "Note 2"
      ],
      "Id": 13,
      "TimeStamp": "2021-05-24T20:37:29.1203005+01:00"
    },
    {
      "Title": "Update TestUpdated 1",
      "Items": [
        "Note 1",
        "Note 2",
        "Note 3"
      ],
      "Id": 14,
      "TimeStamp": "0001-01-01T00:00:00"
    },
    {
      "Title": "Delete Test",
      "Items": [
        "Note 1",
        "Note 2"
      ],
      "Id": 15,
      "TimeStamp": "2021-05-24T20:39:38.9489255+01:00"
    },
    {
      "Title": "Todo Note Postman test",
      "Items": [
        "Postman 1",
        "Postman 2"
      ],
      "Id": 16,
      "TimeStamp": "2021-05-24T20:45:06.55034+01:00"
    },
    {
      "Title": "Todo Note Test",
      "Items": [
        "Note 1",
        "Note 2"
      ],
      "Id": 18,
      "TimeStamp": "2021-05-24T20:51:22.0110488+01:00"
    },
    {
      "Title": "Update TestUpdated 1",
      "Items": [
        "Note 1",
        "Note 2",
        "Note 3"
      ],
      "Id": 19,
      "TimeStamp": "0001-01-01T00:00:00"
    },
    {
      "Title": "GetById Test1",
      "Items": [
        "Note 1 Test 1",
        "Note 2 Test 1"
      ],
      "Id": 21,
      "TimeStamp": "2021-05-24T20:51:22.1217321+01:00"
    },
    {
      "Title": "GetById Test2",
      "Items": [
        "Note 1 Test 2",
        "Note 2 Test 2"
      ],
      "Id": 22,
      "TimeStamp": "2021-05-24T20:51:22.1295637+01:00"
    }
  ],
  "ActualId": 22
}